Metadata-Version: 2.4
Name: iflow-mcp_gbaeke_mcp-obo
Version: 0.1.1
Summary: MCP Server with Azure Entra ID Authentication and OBO flow for Microsoft Search
Requires-Python: >=3.8
Requires-Dist: aiohttp
Requires-Dist: azure-identity
Requires-Dist: azure-search-documents>=11.6.0
Requires-Dist: click
Requires-Dist: fastmcp
Requires-Dist: ipykernel
Requires-Dist: msgraph-sdk
Requires-Dist: pyjwt
Requires-Dist: python-dotenv
Requires-Dist: requests
